odoo/addons/stock_orderpoint_no_horizon/README.rst
odoo/addons/stock_orderpoint_no_horizon/__init__.py
odoo/addons/stock_orderpoint_no_horizon/__manifest__.py
odoo/addons/stock_orderpoint_no_horizon/i18n/it.po
odoo/addons/stock_orderpoint_no_horizon/i18n/stock_orderpoint_no_horizon.pot
odoo/addons/stock_orderpoint_no_horizon/models/__init__.py
odoo/addons/stock_orderpoint_no_horizon/models/stock_warehouse_orderpoint.py
odoo/addons/stock_orderpoint_no_horizon/readme/CONTRIBUTORS.md
odoo/addons/stock_orderpoint_no_horizon/readme/DESCRIPTION.md
odoo/addons/stock_orderpoint_no_horizon/static/description/icon.png
odoo/addons/stock_orderpoint_no_horizon/static/description/index.html
odoo/addons/stock_orderpoint_no_horizon/tests/__init__.py
odoo/addons/stock_orderpoint_no_horizon/tests/test_orderpoint_no_horizon.py
odoo_addon_stock_orderpoint_no_horizon-18.0.1.0.0.5.dist-info/METADATA
odoo_addon_stock_orderpoint_no_horizon-18.0.1.0.0.5.dist-info/WHEEL
odoo_addon_stock_orderpoint_no_horizon-18.0.1.0.0.5.dist-info/top_level.txt
odoo_addon_stock_orderpoint_no_horizon-18.0.1.0.0.5.dist-info/RECORD
