Metadata-Version: 2.1
Name: odoo-addon-stock_orderpoint_no_horizon
Version: 18.0.1.0.0.5
Requires-Python: >=3.10
Requires-Dist: odoo==18.0.*
Summary: Consider all future moves, do not limit horizon to the rule lead days.
Home-page: https://github.com/OCA/stock-logistics-orderpoint
License: AGPL-3
Author: Camptocamp, BCIM, Odoo Community Association (OCA)
Author-email: support@odoo-community.org
Classifier: Programming Language :: Python
Classifier: Framework :: Odoo
Classifier: Framework :: Odoo :: 18.0
Classifier: License :: OSI Approved :: GNU Affero General Public License v3
